LICENSE.txt
MANIFEST.in
README.md
setup.py
QPtomographer/__init__.py
QPtomographer/_version.py
QPtomographer/util.py
QPtomographer.egg-info/PKG-INFO
QPtomographer.egg-info/SOURCES.txt
QPtomographer.egg-info/dependency_links.txt
QPtomographer.egg-info/not-zip-safe
QPtomographer.egg-info/requires.txt
QPtomographer.egg-info/top_level.txt
cxx/channelspace.h
cxx/diamond_norm_figofmerit.h
cxx/diamond_norm_scs.h
cxx/entglfidelity_figofmerit.h
cxx/pydnormbistates.cxx
cxx/pydnormchannelspace.cxx
cxx/pyfigofmerit.cxx
cxx/pyutils.h
cxx/qptomo_use_scs.h
cxx/test_channelspace.cxx
cxx/test_diamond_norm.cxx
cxx/test_utils.cxx
cxx/testutils.h
cxx/utils.h
cxx/worstentglfidelity_figofmerit.h
doc/Makefile
doc/QPtomographer._members.rst
doc/QPtomographer.bistates.rst
doc/QPtomographer.channelspace.rst
doc/QPtomographer.figofmerit.rst
doc/QPtomographer.rst
doc/QPtomographer.util.rst
doc/api_conventions.rst
doc/conf.py
doc/figures_of_merit.rst
doc/index.rst
doc/install.rst
doc/make.bat
doc/_static/QPtomographer.svg
doc/_static/custom.css