Metadata-Version: 1.0
Name: QPtomographer
Version: 1.0
Summary: Reliable Diamond Norm Estimation for Quantum Process Tomography
Home-page: UNKNOWN
Author: Philippe Faist
Author-email: phfaist@caltech.edu
License: UNKNOWN
Platform: UNKNOWN
